{
    "name": "AoyamaTeam2",
    "senario": "scene1_Day6",
    "answers": [
        [
            {
                "time": "00h-00m-16s",
                "place": "bedroom",
                "obj": "pillow"
            },
            {
                "time": "00h-01m-00s",
                "place": "bathroom",
                "obj": "barsoap"
            },
            {
                "time": "00h-02m-55s",
                "place": "livingroom",
                "obj": "remotecontrol"
            },
            {
                "time": "00h-03m-05s",
                "place": "kitchen",
                "obj": "milk"
            },
            {
                "time": "00h-03m-28s",
                "place": "kitchen",
                "obj": "cutleryfork"
            },
            {
                "time": "00h-03m-38s",
                "place": "kitchen",
                "obj": "cutleryfork"
            },
            {
                "time": "00h-04m-03s",
                "place": "kitchen",
                "obj": "alcohol"
            },
            {
                "time": "00h-05m-19s",
                "place": "kitchen",
                "obj": "alcohol"
            },
            {
                "time": "00h-05m-35s",
                "place": "bathroom",
                "obj": "towel"
            },
            {
                "time": "00h-05m-51s",
                "place": "kitchen",
                "obj": "crackers"
            },
            {
                "time": "00h-07m-11s",
                "place": "kitchen",
                "obj": "milk"
            },
            {
                "time": "00h-07m-35s",
                "place": "kitchen",
                "obj": "waterglass"
            },
            {
                "time": "00h-07m-54s",
                "place": "kitchen",
                "obj": "cutleryfork"
            },
            {
                "time": "00h-08m-23s",
                "place": "kitchen",
                "obj": "wineglass"
            },
            {
                "time": "00h-08m-33s",
                "place": "kitchen",
                "obj": "wine"
            },
            {
                "time": "00h-08m-49s",
                "place": "kitchen",
                "obj": "plate"
            },
            {
                "time": "00h-09m-04s",
                "place": "kitchen",
                "obj": "waterglass"
            },
            {
                "time": "00h-09m-33s",
                "place": "kitchen",
                "obj": "cutleryknife"
            },
            {
                "time": "00h-09m-45s",
                "place": "bedroom",
                "obj": "clothespants"
            },
            {
                "time": "00h-09m-54s",
                "place": "bedroom",
                "obj": "clothespile"
            },
            {
                "time": "00h-10m-03s",
                "place": "bedroom",
                "obj": "clothesshirt"
            },
            {
                "time": "00h-10m-06s",
                "place": "bedroom",
                "obj": "clothespants"
            },
            {
                "time": "00h-10m-47s",
                "place": "bedroom",
                "obj": "clothespile"
            },
            {
                "time": "00h-11m-05s",
                "place": "bedroom",
                "obj": "clothespants"
            },
            {
                "time": "00h-11m-08s",
                "place": "bedroom",
                "obj": "clothesshirt"
            },
            {
                "time": "00h-11m-41s",
                "place": "bedroom",
                "obj": "clothespile"
            },
            {
                "time": "00h-12m-29s",
                "place": "livingroom",
                "obj": "remotecontrol"
            },
            {
                "time": "00h-12m-37s",
                "place": "kitchen",
                "obj": "breadslice"
            },
            {
                "time": "00h-13m-42s",
                "place": "kitchen",
                "obj": "milk"
            },
            {
                "time": "00h-14m-06s",
                "place": "kitchen",
                "obj": "waterglass"
            },
            {
                "time": "00h-14m-32s",
                "place": "kitchen",
                "obj": "washingsponge"
            },
            {
                "time": "00h-15m-18s",
                "place": "kitchen",
                "obj": "milk"
            },
            {
                "time": "00h-16m-01s",
                "place": "kitchen",
                "obj": "dishbowl"
            },
            {
                "time": "00h-16m-20s",
                "place": "kitchen",
                "obj": "cereal"
            }
        ]
    ]
}