{
    "name": "AoyamaTeam2",
    "senario": "scene6_Day10",
    "answers": [
        {
            "name": "walk",
            "number": 37
        },
        {
            "name": "grab",
            "number": 11
        },
        {
            "name": "put",
            "number": 8
        },
        {
            "name": "sit",
            "number": 3
        },
        {
            "name": "switchOn",
            "number": 2
        },
        {
            "name": "wipe",
            "number": 2
        },
        {
            "name": "read",
            "number": 2
        },
        {
            "name": "drink",
            "number": 2
        },
        {
            "name": "switchOff",
            "number": 2
        },
        {
            "name": "stand",
            "number": 1
        },
        {
            "name": "open",
            "number": 1
        },
        {
            "name": "close",
            "number": 1
        },
        {
            "name": "soak",
            "number": 1
        },
        {
            "name": "turnTo",
            "number": 1
        },
        {
            "name": "fall",
            "number": 1
        },
        {
            "name": "throw",
            "number": 1
        },
        {
            "name": "shake",
            "number": 1
        }
    ]
}