{
    "name": "AoyamaTeam2",
    "senario": "scene4_Day9",
    "answers": [
        [
            {
                "time": "00h-00m-19s",
                "place": "kitchen",
                "obj": "washingsponge"
            },
            {
                "time": "00h-01m-16s",
                "place": "kitchen",
                "obj": "cutleryfork"
            },
            {
                "time": "00h-01m-39s",
                "place": "kitchen",
                "obj": "wineglass"
            },
            {
                "time": "00h-01m-45s",
                "place": "kitchen",
                "obj": "wine"
            },
            {
                "time": "00h-01m-59s",
                "place": "kitchen",
                "obj": "plate"
            },
            {
                "time": "00h-02m-12s",
                "place": "kitchen",
                "obj": "waterglass"
            },
            {
                "time": "00h-02m-34s",
                "place": "kitchen",
                "obj": "cutleryknife"
            },
            {
                "time": "00h-02m-41s",
                "place": "kitchen",
                "obj": "cutleryfork"
            },
            {
                "time": "00h-02m-51s",
                "place": "kitchen",
                "obj": "cutleryfork"
            },
            {
                "time": "00h-03m-20s",
                "place": "kitchen",
                "obj": "cutleryknife"
            },
            {
                "time": "00h-03m-26s",
                "place": "kitchen",
                "obj": "cutleryknife"
            },
            {
                "time": "00h-03m-47s",
                "place": "kitchen",
                "obj": "potato"
            },
            {
                "time": "00h-03m-58s",
                "place": "kitchen",
                "obj": "salad"
            },
            {
                "time": "00h-04m-30s",
                "place": "kitchen",
                "obj": "washingsponge"
            },
            {
                "time": "00h-06m-54s",
                "place": "bathroom",
                "obj": "toothbrush"
            },
            {
                "time": "00h-06m-59s",
                "place": "bathroom",
                "obj": "toothpaste"
            },
            {
                "time": "00h-07m-58s",
                "place": "kitchen",
                "obj": "plate"
            },
            {
                "time": "00h-08m-07s",
                "place": "kitchen",
                "obj": "plate"
            },
            {
                "time": "00h-08m-55s",
                "place": "bedroom",
                "obj": "book"
            },
            {
                "time": "00h-09m-25s",
                "place": "bedroom",
                "obj": "notes"
            },
            {
                "time": "00h-09m-49s",
                "place": "bathroom",
                "obj": "toothbrush"
            },
            {
                "time": "00h-09m-54s",
                "place": "bathroom",
                "obj": "toothpaste"
            },
            {
                "time": "00h-11m-00s",
                "place": "livingroom",
                "obj": "box"
            }
        ]
    ]
}